snmpsim_data/__init__.py
thola_snmpsim_data-0.0.3.data/data/snmpsim_data/data/UPS/apc-7902b.snmprec
thola_snmpsim_data-0.0.3.data/data/snmpsim_data/data/UPS/apc-8641.snmprec
thola_snmpsim_data-0.0.3.data/data/snmpsim_data/data/UPS/apc-8932.snmprec
thola_snmpsim_data-0.0.3.data/data/snmpsim_data/data/UPS/raritan-px3-5260r.snmprec
thola_snmpsim_data-0.0.3.data/data/snmpsim_data/data/iot/geist-temperature-sensor.snmprec
thola_snmpsim_data-0.0.3.data/data/snmpsim_data/data/network/appliance/tripplite-poweralert.snmprec
thola_snmpsim_data-0.0.3.dist-info/LICENSE.txt
thola_snmpsim_data-0.0.3.dist-info/METADATA
thola_snmpsim_data-0.0.3.dist-info/WHEEL
thola_snmpsim_data-0.0.3.dist-info/top_level.txt
thola_snmpsim_data-0.0.3.dist-info/RECORD
